{
  "type": "minecraft:random_patch",
  "config": {
    "tries": 2,
    "xz_spread": 3,
    "feature": {
      "feature": {
        "type": "minecraft:replace_single_block",
        "config": {
          "targets": [
            {
              "target": {
                "predicate_type": "minecraft:block_match",
                "block": "lunarnether:lunar_stone"
              },
              "state": {
                "Name": "minecraft:air"
              }
            }
          ]
        }
      },
      "placement": [
        {
          "type": "minecraft:height_range",
          "height": {
            "absolute": 127
          }
        },
        {
          "type": "minecraft:count",
          "count": 16
        },
        {
          "type": "minecraft:in_square"
        },
        {
          "type": "minecraft:environment_scan",
          "direction_of_search": "down",
          "max_steps": 2,
          "target_condition": {
            "type": "minecraft:matching_blocks",
            "blocks": "minecraft:air"
          }
        }
      ]
    }
  }
}
